cartesia_mlx/__init__.py
cartesia_mlx/version.py
cartesia_mlx/layers/__init__.py
cartesia_mlx/layers/embedding.py
cartesia_mlx/layers/ffn.py
cartesia_mlx/layers/linear.py
cartesia_mlx/layers/phi_block.py
cartesia_mlx/layers/residual_block.py
cartesia_mlx/layers/sa.py
cartesia_mlx/layers/sequence_model.py
cartesia_mlx/layers/ssd/__init__.py
cartesia_mlx/layers/ssd/llamba_ssd.py
cartesia_mlx/layers/ssd/mohawk_ssd.py
cartesia_mlx/layers/ssd/ops.py
cartesia_mlx/layers/ssd/ssd.py
cartesia_mlx/models/__init__.py
cartesia_mlx/models/llamba.py
cartesia_mlx/models/lm.py
cartesia_mlx/models/mamba2.py
cartesia_mlx/models/mohawk.py
cartesia_mlx/models/rene.py
cartesia_mlx/utils/configure.py
cartesia_mlx/utils/filter.py
cartesia_mlx/utils/load.py
cartesia_mlx/utils/registry.py
cartesia_mlx/utils/sample_utils.py
cartesia_mlx/utils/tokenizer.py
cartesia_mlx-0.0.2.dist-info/METADATA
cartesia_mlx-0.0.2.dist-info/WHEEL
cartesia_mlx-0.0.2.dist-info/top_level.txt
cartesia_mlx-0.0.2.dist-info/RECORD
