Metadata-Version: 2.2
Name: cartesia-mlx
Version: 0.0.2
Summary: The official Cartesia MLX library.
Home-page: https://github.com/cartesia-ai/edge
Author: Cartesia, Inc.
Author-email: support@cartesia.ai
Classifier: Programming Language :: Python
Classifier: Programming Language :: Python :: 3
Classifier: Topic :: Scientific/Engineering :: Artificial Intelligence
Requires-Python: >=3.9.0
Requires-Dist: mlx==0.22.1
Requires-Dist: nanobind==2.4.0
Requires-Dist: transformers>=4.40.0
Requires-Dist: datasets
Requires-Dist: torch
Requires-Dist: numpy<2
Requires-Dist: requests
Requires-Dist: huggingface_hub
Dynamic: author
Dynamic: author-email
Dynamic: classifier
Dynamic: description
Dynamic: description-content-type
Dynamic: home-page
Dynamic: requires-dist
Dynamic: requires-python
Dynamic: summary
